{
  "COMMON": {
    "RAW_CSV_PATH": "./data/sample.csv",
    "STOPWORDS_PATH": "./data/stopwords.csv",
    "DATE_COL_NAME": "date",
    "KEYWORD_COL_NAME": "keyword"
  },
  "OPTIMIZE": {
    "CHUNK_SIZE": 2000,
    "ITERATION": 10,
    "GET_PASSES_N_TOPICS": 10,
    "GET_PASSES_MAX_N_PASSES": 1,
    "GET_TOPICS_N_PASSES": 5,
    "GET_PASSES_MAX_N_TOPICS": 1,
    "RESULT_DIR_PATH": "./result/sample/optimize"
  },
  "EDA": {
    "NUM_OF_ARTICLES_GRAPH_PATH": "./result/sample/num_of_articles.png",
    "TOP_FREQ_N": 30,
    "TOP_FREQ_WORDS_GRAPH_PATH": "./result/sample/top_freq.png"
  },
  "VECTORIZER": {
    "MAX_FEATURES": 100000,
    "TFIDF_NGRAM_MAX": 2,
    "TFIDF_MAX_DF": 1.0,
    "TFIDF_MIN_DF": 1
  },
  "TM": {
    "N_TOPICS": 5,
    "N_ITER": 10,
    "RANDOM_STATE": 0
  },
  "RESULT_TOPIC_WORDS": {
    "WORD_COUNT": 30,
    "CSV_PATH": "./result/sample/topic_words.csv",
    "GRAPH_PATH": "./result/sample/topic_words.png"
  },
  "RESULT_YEAR_TOPIC_DENSITY": {
    "START_YEAR": 2022,
    "END_YEAR": 2022,
    "CSV_PATH": "./result/sample/year_count.csv",
    "GRAPH_PATH": "./result/sample/year_count.png"
  },
  "RESULT_TSNE": {
    "N_COMPONENTS": 2,
    "PERPLEXITY": 50,
    "LEARNING_RATE": 100,
    "N_ITER": 250,
    "RANDOM_STATE": 0,
    "ANGLE": 0.75,
    "N_JOBS": -1,
    "GRAPH_PATH": "./result/sample/tsne.html"
  },
  "RESULT_LDAVIS": {
    "GRAPH_PATH": "./result/sample/ldavis.html"
  },
  "DUMP": {
    "MODEL_PATH": "./model/lda_model.bin",
    "TOPIC_MATRIX_PATH": "./model/topic_matrix.bin"
  },
  "TOPIC_DISTRIBUTION": {
    "TOP_N": 10,
    "CSV_PATH": "./result/sample/topic_distribution.csv"
  }
}